skyhookfilecrypt
