Metadata-Version: 2.1
Name: skyhookfilecrypt
Version: 1.1
Summary: File encryption and decryption module extracted from Skyhook
Home-page: https://github.com/deedeecx330/skyhookfilecrypt
Author: deedeecx330
License: GNU General Public Licence v3 (GPLv3)
Keywords: aes cbc encrypt decrypt cryptography file
Platform: UNKNOWN
Classifier: Operating System :: OS Independent
Classifier: Programming Language :: Python :: 3
Classifier: Topic :: Security
Classifier: Topic :: Security :: Cryptography
Classifier: Topic :: Utilities
